setup.py
alebot/__init__.py
alebot/cli.py
alebot.egg-info/PKG-INFO
alebot.egg-info/SOURCES.txt
alebot.egg-info/dependency_links.txt
alebot.egg-info/entry_points.txt
alebot.egg-info/not-zip-safe
alebot.egg-info/requires.txt
alebot.egg-info/top_level.txt
alebot/plugins/__init__.py
alebot/plugins/admin.py
alebot/plugins/auth.py
alebot/plugins/channels.py
alebot/plugins/default.py
alebot/plugins/shortlink.py