Metadata-Version: 1.0
Name: alebot
Version: 0.1.2
Summary: A super lean and highly modularized irc bot
Home-page: https://github.com/alexex/alebot
Author: Alexander Jung-Loddenkemper
Author-email: alexander@julo.ch
License: MIT
Platform: any
